fakedb/__init__.py
fakedb/fake_mongo.py
fakedb/fake_postgres.py
fakedb/model_adapters.py
fakedb/storage_backends.py
fakedb/.ipynb_checkpoints/fake_mongo-checkpoint.py
fakedb/.ipynb_checkpoints/fake_postgres-checkpoint.py
fakedb-0.1.0.dist-info/METADATA
fakedb-0.1.0.dist-info/WHEEL
fakedb-0.1.0.dist-info/top_level.txt
fakedb-0.1.0.dist-info/RECORD
