Metadata-Version: 2.4
Name: fakedb
Version: 0.1.0
Summary: Asynchronous fake PostgreSQL and MongoDB interfaces backed by local or remote storage.
Author: Fake GCS DB Maintainers
License: MIT
Project-URL: Home, https://github.com/eduardo/fakedb
Project-URL: Source, https://github.com/eduardo/fakedb
Keywords: gcs,postgresql,mongodb,asyncio,testing
Requires-Python: >=3.9
Provides-Extra: extras
Requires-Dist: pydantic>=1.10; extra == "extras"
Requires-Dist: sqlmodel>=0.0.8; extra == "extras"
Requires-Dist: sqlalchemy>=1.4; extra == "extras"
Provides-Extra: cloud
Requires-Dist: google-cloud-storage>=2.0; extra == "cloud"
Provides-Extra: dev
Requires-Dist: pytest>=7; extra == "dev"
Requires-Dist: pytest-asyncio>=0.21; extra == "dev"
Requires-Dist: pytest-cov>=4; extra == "dev"
